xtnkk_tools/MongoDB.py
xtnkk_tools/__init__.py
xtnkk_tools/tools.py
xtnkk_tools/tools_time.py
xtnkk_tools/update.py
xtnkk_tools/db/MongoDB.py
xtnkk_tools/db/__init__.py
xtnkk_tools-1.0.1.5.dist-info/LICENSE
xtnkk_tools-1.0.1.5.dist-info/METADATA
xtnkk_tools-1.0.1.5.dist-info/WHEEL
xtnkk_tools-1.0.1.5.dist-info/top_level.txt
xtnkk_tools-1.0.1.5.dist-info/RECORD
